tgzr/pipeline/__init__.py
tgzr/pipeline/_version.py
tgzr/pipeline/main.py
tgzr/pipeline/tgzr_cli_plugin.py
tgzr/pipeline/workspace.py
tgzr/pipeline/asset/__init__.py
tgzr/pipeline/asset/asset.py
tgzr/pipeline/asset/manager.py
tgzr/pipeline/asset/plugin.py
tgzr/pipeline/asset/asset_plugins/__init__.py
tgzr/pipeline/asset/asset_plugins/builder.py
tgzr/pipeline/asset/asset_plugins/casting.py
tgzr/pipeline/asset/asset_plugins/creator.py
tgzr/pipeline/asset/asset_plugins/env.py
tgzr/pipeline/asset/asset_plugins/workscene.py
tgzr/pipeline/asset/asset_plugins/asset_with_params/__init__.py
tgzr/pipeline/asset/asset_plugins/asset_with_params/params_panel.py
tgzr/pipeline/asset/asset_plugins/asset_with_params/xx.py
tgzr/pipeline/cli/__init__.py
tgzr/pipeline/cli/utils.py
tgzr/pipeline/hatch/README.md
tgzr/pipeline/hatch/__init__.py
tgzr/pipeline/hatch/metadata_hook.py
tgzr/pipeline/hatch/plugins.py
tgzr/pipeline/hatch/publisher.py
tgzr_pipeline-0.102.dist-info/METADATA
tgzr_pipeline-0.102.dist-info/WHEEL
tgzr_pipeline-0.102.dist-info/entry_points.txt
tgzr_pipeline-0.102.dist-info/licenses/LICENSE
tgzr_pipeline-0.102.dist-info/RECORD
