Metadata-Version: 2.4
Name: tgzr.pipeline
Version: 0.102
Summary: tgzr pipeline engine
Project-URL: Documentation, https://github.com/open-tgzr/tgzr.pipeline#readme
Project-URL: Issues, https://github.com/open-tgzr/tgzr.pipeline/issues
Project-URL: Source, https://github.com/open-tgzr/tgzr.pipeline
Author-email: Dee <dee.sometech@gmail.com>
License-Expression: GPL-3.0-or-later
License-File: LICENSE
Classifier: Development Status :: 4 - Beta
Classifier: Programming Language :: Python
Classifier: Programming Language :: Python :: 3.8
Classifier: Programming Language :: Python :: 3.9
Classifier: Programming Language :: Python :: 3.10
Classifier: Programming Language :: Python :: 3.11
Classifier: Programming Language :: Python :: 3.12
Classifier: Programming Language :: Python :: Implementation :: CPython
Classifier: Programming Language :: Python :: Implementation :: PyPy
Requires-Python: >=3.9
Requires-Dist: click
Requires-Dist: eval-type-backport
Requires-Dist: hatch
Requires-Dist: importlib-metadata
Requires-Dist: pydantic
Requires-Dist: rich
Requires-Dist: tgzr-package-management
Requires-Dist: toml
Requires-Dist: uv
